Metadata-Version: 2.1
Name: ix-gimad
Version: 0.1.1
Summary: Non-schema database migration tool for PostgreSQL
Author-Email: injuryex <injuryex@ptnglobalcorp.com>
Project-URL: Source, https://github.com/ptnglobalcorp/gimad
Requires-Python: >=3.12
Requires-Dist: psycopg[binary]
Requires-Dist: typer
Requires-Dist: pydantic-settings
